plimsolls/__init__.py
plimsolls/formatters/__init__.py
plimsolls/formatters/code2html.py
plimsolls-1.0.dist-info/DESCRIPTION.rst
plimsolls-1.0.dist-info/METADATA
plimsolls-1.0.dist-info/RECORD
plimsolls-1.0.dist-info/WHEEL
plimsolls-1.0.dist-info/metadata.json
plimsolls-1.0.dist-info/top_level.txt
