Metadata-Version: 2.0
Name: plimsolls
Version: 1.0
Summary: Presentation helpers based on Plim
Home-page: https://github.com/keitheis/plimsolls/
Author: Keith Yang
Author-email: yang@keitheis.org
License: MIT
Keywords: html presentations slides plim templates
Platform: any
Classifier: Development Status :: 4 - Beta
Classifier: Topic :: Text Processing
Classifier: Topic :: Multimedia :: Graphics :: Presentation
Classifier: Intended Audience :: Developers
Classifier: Environment :: Console
Classifier: Operating System :: OS Independent
Classifier: License :: OSI Approved :: MIT License
Classifier: Programming Language :: Python
Classifier: Programming Language :: Python :: 3
Classifier: Programming Language :: Python :: 2.7
Requires-Dist: Plim (>=0.9.12)
Requires-Dist: Pygments (>=2.0.2)
